TongguoCeshiXuexiGoBiancheng/README.md
TongguoCeshiXuexiGoBiancheng/__init__.py
TongguoCeshiXuexiGoBiancheng/__main__.py
TongguoCeshiXuexiGoBiancheng/file.epub
TongguoCeshiXuexiGoBiancheng/index.html
TongguoCeshiXuexiGoBiancheng/css/__init__.py
TongguoCeshiXuexiGoBiancheng/css/annotations.css
TongguoCeshiXuexiGoBiancheng/css/main.css
TongguoCeshiXuexiGoBiancheng/css/normalize.css
TongguoCeshiXuexiGoBiancheng/css/popup.css
TongguoCeshiXuexiGoBiancheng/font/__init__.py
TongguoCeshiXuexiGoBiancheng/font/fontello.eot
TongguoCeshiXuexiGoBiancheng/font/fontello.svg
TongguoCeshiXuexiGoBiancheng/font/fontello.ttf
TongguoCeshiXuexiGoBiancheng/font/fontello.woff
TongguoCeshiXuexiGoBiancheng/img/__init__.py
TongguoCeshiXuexiGoBiancheng/img/annotator-glyph-sprite.png
TongguoCeshiXuexiGoBiancheng/img/annotator-icon-sprite.png
TongguoCeshiXuexiGoBiancheng/img/apple-touch-icon.png
TongguoCeshiXuexiGoBiancheng/img/cancelfullscreen.png
TongguoCeshiXuexiGoBiancheng/img/close.png
TongguoCeshiXuexiGoBiancheng/img/fullscreen.png
TongguoCeshiXuexiGoBiancheng/img/loader.gif
TongguoCeshiXuexiGoBiancheng/img/menu-icon.png
TongguoCeshiXuexiGoBiancheng/img/save.png
TongguoCeshiXuexiGoBiancheng/img/saved.png
TongguoCeshiXuexiGoBiancheng/img/settings-s.png
TongguoCeshiXuexiGoBiancheng/img/settings.png
TongguoCeshiXuexiGoBiancheng/img/star.png
TongguoCeshiXuexiGoBiancheng/js/__init__.py
TongguoCeshiXuexiGoBiancheng/js/epub.js
TongguoCeshiXuexiGoBiancheng/js/epub.min.js
TongguoCeshiXuexiGoBiancheng/js/epub.min.map
TongguoCeshiXuexiGoBiancheng/js/hooks.min.js
TongguoCeshiXuexiGoBiancheng/js/hooks.min.map
TongguoCeshiXuexiGoBiancheng/js/reader.js
TongguoCeshiXuexiGoBiancheng/js/reader.js.map
TongguoCeshiXuexiGoBiancheng/js/reader.min.js
TongguoCeshiXuexiGoBiancheng/js/reader.min.map
TongguoCeshiXuexiGoBiancheng/js/hooks/__init__.py
TongguoCeshiXuexiGoBiancheng/js/hooks/extensions/__init__.py
TongguoCeshiXuexiGoBiancheng/js/hooks/extensions/highlight.js
tongguo_ceshi_xuexi_go_biancheng-2024.3.6.0.dist-info/METADATA
tongguo_ceshi_xuexi_go_biancheng-2024.3.6.0.dist-info/WHEEL
tongguo_ceshi_xuexi_go_biancheng-2024.3.6.0.dist-info/entry_points.txt
tongguo_ceshi_xuexi_go_biancheng-2024.3.6.0.dist-info/top_level.txt
tongguo_ceshi_xuexi_go_biancheng-2024.3.6.0.dist-info/RECORD
